[
  {
    "number": 1,
    "text": "Os que confiam no Senhor são como o monte Sião, que não se abala, firme para sempre."
  },
  {
    "number": 2,
    "text": "Como em redor de Jerusalém estão os montes, assim o Senhor, em derredor do seu povo, desde agora e para sempre."
  },
  {
    "number": 3,
    "text": "O cetro dos ímpios não permanecerá sobre a sorte dos justos, para que o justo não estenda a mão à iniquidade."
  },
  {
    "number": 4,
    "text": "Faze o bem, Senhor, aos bons e aos retos de coração."
  },
  {
    "number": 5,
    "text": "Quanto aos que se desviam para sendas tortuosas, levá-los-á o Senhor juntamente com os malfeitores. Paz sobre Israel!"
  }
]
